{
  "annotations": {
    "list": [
      {
        "builtIn": 1,
        "datasource": "-- Grafana --",
        "enable": false,
        "hide": true,
        "iconColor": "rgba(0, 211, 255, 1)",
        "limit": 100,
        "name": "Annotations & Alerts",
        "showIn": 0,
        "type": "dashboard"
      }
    ]
  },
  "editable": true,
  "gnetId": null,
  "graphTooltip": 0,
  "iteration": 1605411055202,
  "links": [],
  "panels": [
    {
      "aliasColors": {
        "co2": "super-light-blue"
      },
      "bars": false,
      "dashLength": 10,
      "dashes": false,
      "datasource": null,
      "fieldConfig": {
        "defaults": {
          "custom": {},
          "mappings": [],
          "thresholds": {
            "mode": "absolute",
            "steps": [
              {
                "color": "green",
                "value": null
              },
              {
                "color": "#EAB839",
                "value": 1000
              },
              {
                "color": "red",
                "value": 2000
              }
            ]
          }
        },
        "overrides": []
      },
      "fill": 1,
      "fillGradient": 0,
      "gridPos": {
        "h": 8,
        "w": 5,
        "x": 0,
        "y": 0
      },
      "hiddenSeries": false,
      "id": 13,
      "legend": {
        "avg": false,
        "current": false,
        "max": false,
        "min": false,
        "show": true,
        "total": false,
        "values": false
      },
      "lines": true,
      "linewidth": 1,
      "nullPointMode": "null",
      "options": {
        "alertThreshold": true
      },
      "percentage": false,
      "pluginVersion": "7.3.2",
      "pointradius": 2,
      "points": false,
      "renderer": "flot",
      "repeat": null,
      "repeatDirection": "h",
      "seriesOverrides": [],
      "spaceLength": 10,
      "stack": false,
      "steppedLine": false,
      "targets": [
        {
          "alias": "co2",
          "groupBy": [
            {
              "params": [
                "$__interval"
              ],
              "type": "time"
            },
            {
              "params": [
                "null"
              ],
              "type": "fill"
            }
          ],
          "measurement": "mqtt_consumer",
          "orderByTime": "ASC",
          "policy": "default",
          "query": "SELECT distinct(\"value\") FROM \"mqtt_consumer\" WHERE (\"topic\" =~ /^$Raum$/) AND $timeFilter GROUP BY time($__interval) fill(null)",
          "rawQuery": false,
          "refId": "A",
          "resultFormat": "time_series",
          "select": [
            [
              {
                "params": [
                  "value"
                ],
                "type": "field"
              },
              {
                "params": [],
                "type": "distinct"
              }
            ]
          ],
          "tags": [
            {
              "key": "topic",
              "operator": "=~",
              "value": "/^classroom\\/$Raum\\/co2$/"
            }
          ]
        }
      ],
      "thresholds": [
        {
          "$$hashKey": "object:83",
          "colorMode": "critical",
          "fill": true,
          "fillColor": "#C4162A",
          "line": false,
          "lineColor": "rgba(31, 96, 196, 0.6)",
          "op": "gt",
          "value": 2000,
          "yaxis": "left"
        },
        {
          "$$hashKey": "object:84",
          "colorMode": "warning",
          "fill": true,
          "line": false,
          "op": "gt",
          "value": 1250,
          "yaxis": "left"
        },
        {
          "$$hashKey": "object:85",
          "colorMode": "ok",
          "fill": true,
          "line": false,
          "op": "lt",
          "value": 1250,
          "yaxis": "left"
        }
      ],
      "timeFrom": null,
      "timeRegions": [],
      "timeShift": null,
      "title": "CO2",
      "tooltip": {
        "shared": true,
        "sort": 0,
        "value_type": "individual"
      },
      "type": "graph",
      "xaxis": {
        "buckets": null,
        "mode": "time",
        "name": null,
        "show": true,
        "values": []
      },
      "yaxes": [
        {
          "format": "ppm",
          "label": "",
          "logBase": 1,
          "max": null,
          "min": null,
          "show": true
        },
        {
          "format": "short",
          "label": null,
          "logBase": 1,
          "max": null,
          "min": null,
          "show": false
        }
      ],
      "yaxis": {
        "align": false,
        "alignLevel": null
      }
    },
    {
      "datasource": null,
      "fieldConfig": {
        "defaults": {
          "custom": {},
          "mappings": [],
          "thresholds": {
            "mode": "absolute",
            "steps": [
              {
                "color": "dark-blue",
                "value": null
              },
              {
                "color": "dark-green",
                "value": 20
              },
              {
                "color": "#EAB839",
                "value": 25
              },
              {
                "color": "red",
                "value": 30
              }
            ]
          },
          "unit": "celsius"
        },
        "overrides": []
      },
      "gridPos": {
        "h": 8,
        "w": 5,
        "x": 5,
        "y": 0
      },
      "id": 14,
      "options": {
        "colorMode": "value",
        "graphMode": "area",
        "justifyMode": "auto",
        "orientation": "auto",
        "reduceOptions": {
          "calcs": [
            "last"
          ],
          "fields": "",
          "values": false
        },
        "textMode": "auto"
      },
      "pluginVersion": "7.3.2",
      "repeatDirection": "h",
      "targets": [
        {
          "alias": "co2",
          "groupBy": [
            {
              "params": [
                "$__interval"
              ],
              "type": "time"
            },
            {
              "params": [
                "null"
              ],
              "type": "fill"
            }
          ],
          "measurement": "mqtt_consumer",
          "orderByTime": "ASC",
          "policy": "default",
          "query": "SELECT distinct(\"value\") FROM \"mqtt_consumer\" WHERE (\"topic\" =~ /^classroom\\/$Raum\\/co2$/) AND $timeFilter GROUP BY time($__interval) fill(null)",
          "rawQuery": false,
          "refId": "A",
          "resultFormat": "time_series",
          "select": [
            [
              {
                "params": [
                  "value"
                ],
                "type": "field"
              },
              {
                "params": [],
                "type": "distinct"
              }
            ]
          ],
          "tags": [
            {
              "key": "topic",
              "operator": "=~",
              "value": "/^classroom\\/$Raum\\/temp$/"
            }
          ]
        }
      ],
      "timeFrom": null,
      "timeShift": null,
      "title": "Temperatur",
      "type": "stat"
    },
    {
      "datasource": null,
      "fieldConfig": {
        "defaults": {
          "custom": {},
          "mappings": [],
          "thresholds": {
            "mode": "absolute",
            "steps": [
              {
                "color": "dark-blue",
                "value": null
              },
              {
                "color": "dark-green",
                "value": 40
              },
              {
                "color": "red",
                "value": 60
              }
            ]
          },
          "unit": "humidity"
        },
        "overrides": []
      },
      "gridPos": {
        "h": 8,
        "w": 5,
        "x": 10,
        "y": 0
      },
      "id": 15,
      "options": {
        "colorMode": "value",
        "graphMode": "area",
        "justifyMode": "auto",
        "orientation": "auto",
        "reduceOptions": {
          "calcs": [
            "last"
          ],
          "fields": "",
          "values": false
        },
        "textMode": "auto"
      },
      "pluginVersion": "7.3.2",
      "repeatDirection": "h",
      "targets": [
        {
          "alias": "co2",
          "groupBy": [
            {
              "params": [
                "$__interval"
              ],
              "type": "time"
            },
            {
              "params": [
                "null"
              ],
              "type": "fill"
            }
          ],
          "measurement": "mqtt_consumer",
          "orderByTime": "ASC",
          "policy": "default",
          "query": "SELECT distinct(\"value\") FROM \"mqtt_consumer\" WHERE (\"topic\" =~ /^classroom\\/$Raum\\/co2$/) AND $timeFilter GROUP BY time($__interval) fill(null)",
          "rawQuery": false,
          "refId": "A",
          "resultFormat": "time_series",
          "select": [
            [
              {
                "params": [
                  "value"
                ],
                "type": "field"
              },
              {
                "params": [],
                "type": "distinct"
              }
            ]
          ],
          "tags": [
            {
              "key": "topic",
              "operator": "=~",
              "value": "/^classroom\\/$Raum\\/humidity$/"
            }
          ]
        }
      ],
      "timeFrom": null,
      "timeShift": null,
      "title": "Luftfeuchtigkeit",
      "type": "stat"
    }
  ],
  "schemaVersion": 26,
  "style": "dark",
  "tags": [],
  "templating": {
    "list": [
      {
        "allValue": null,
        "current": {
          "selected": false,
          "text": "Schulleiter",
          "value": "Schulleiter"
        },
        "datasource": "Influxdb",
        "definition": "",
        "error": null,
        "hide": 0,
        "includeAll": false,
        "label": null,
        "multi": false,
        "name": "Raum",
        "options": [],
        "query": "SHOW TAG VALUES WITH key = \"topic\"",
        "refresh": 1,
        "regex": "/classroom\\/(.*)\\/co2/",
        "skipUrlSync": false,
        "sort": 0,
        "tagValuesQuery": "",
        "tags": [],
        "tagsQuery": "",
        "type": "query",
        "useTags": false
      }
    ]
  },
  "time": {
    "from": "now-6h",
    "to": "now"
  },
  "timepicker": {},
  "timezone": "",
  "title": "Detail",
  "uid": "detail",
  "version": 1
}
